{
  "version": 6,
  "cmakeMinimumRequired": {
    "major": 3,
    "minor": 25,
    "patch": 0
  },
  "configurePresets": [
    {
      "name": "release",
      "generator": "Ninja",
      "binaryDir": "${sourceDir}/build/${presetName}",
      "cacheVariables": {
        "CMAKE_BUILD_TYPE": "Release"
      }
    },
    {
      "name": "debug",
      "inherits": "release",
      "cacheVariables": {
        "CMAKE_BUILD_TYPE": "Debug"
      }
    }
  ],
  "buildPresets": [
    {
      "name": "release",
      "configurePreset": "release"
    },
    {
      "name": "debug",
      "configurePreset": "debug"
    }
  ],
  "testPresets": [
    {
      "name": "release",
      "configurePreset": "release",
      "output": {
        "outputOnFailure": true,
        "outputJUnitFile": "junit-report.xml"
      },
      "execution": {
        "scheduleRandom": true,
        "noTestsAction": "error"
      }
    },
    {
      "name": "debug",
      "inherits": "release",
      "configurePreset": "debug"
    }
  ]
}
